02_sequential_basics/02_08_parallel_to_serial/02_08_parallel_to_serial.sv
//----------------------------------------------------------------------------
// Task
//----------------------------------------------------------------------------
// Task:
// Implement a module that converts multi-bit parallel value to the single-bit serial data.
//
// The module should accept 'width' bit input parallel data when 'parallel_valid' input is asserted.
// At the same clock cycle as 'parallel_valid' is asserted, the module should output
// the least significant bit of the input data. In the following clock cycles the module
// should output all the remaining bits of the parallel_data.
// Together with providing correct 'serial_data' value, module should also assert the 'serial_valid' output.
//
// Note:
// Check the waveform diagram in the README for better understanding.

module parallel_to_serial
# (
    parameter width = 8
)
(
    input                      clk,
    input                      rst,

    input                      parallel_valid,
    input        [width - 1:0] parallel_data,

    output                     busy,
    output logic               serial_valid,
    output logic               serial_data
);

    logic [$clog2(width) - 1:0] cnt;
    logic [width - 1:0]         data;
    logic                       busy_reg;

    always_ff @(posedge clk or posedge rst)
        if (rst) begin
            busy_reg <= '0;
            cnt      <= '0;
        end
        else if (parallel_valid & ~busy_reg) begin
            data     <= parallel_data;
            cnt      <= 'd1;
            busy_reg <= '1;
        end
        else if (cnt != width - 1) begin
            cnt <= cnt + 1;
        end
        else if (cnt == width - 1) begin
            busy_reg <= '0;
        end

    assign busy         = busy_reg;
    assign serial_data  = (parallel_valid & ~busy_reg) ? parallel_data[0] : data[cnt];
    assign serial_valid = (parallel_valid & ~busy_reg) ? '1 : busy_reg;;
    

endmodule

02_sequential_basics/02_08_parallel_to_serial/testbench.sv
`include "util.svh"

module testbench;

    // Clock and reset

    logic clk;

    initial
    begin
        clk = '0;

        forever
            # 500 clk = ~ clk;
    end

    logic rst;

    initial
    begin
        rst <= 'x;
        repeat (2) @ (posedge clk);
        rst <= '1;
        repeat (2) @ (posedge clk);
        rst <= '0;
    end

    //------------------------------------------------------------------------

    // Instantiation

    localparam width     = 8;

    localparam n_inputs  = 100;
    localparam n_outputs = n_inputs * width;

    // Minimum to count at least 1000 valid inputs
    localparam in_cnt_w  = $clog2(n_inputs + 1);
    // 8 times smaller than input
    localparam out_cnt_w = $clog2(n_outputs + 1);

    logic                   parallel_valid;
    logic [    width - 1:0] parallel_data;

    wire                    busy;
    wire                    serial_valid;
    wire                    serial_data;

    logic [ in_cnt_w - 1:0] in_vld_cnt;
    logic [out_cnt_w - 1:0] out_vld_cnt;

    parallel_to_serial  # (.width (width)) dut (.*);

    //------------------------------------------------------------------------

    // Monitor

    bit was_reset = 1'b0;

    logic queue [$];
    logic serial_data_expected;

    always @ (posedge clk)
    begin
        if (rst)
        begin
            was_reset   <= 1'b1;
            in_vld_cnt  <= '0;
            out_vld_cnt <= '0;
            queue        = {};
        end
        else if (was_reset)
        begin
            if (parallel_valid) begin
                in_vld_cnt <= in_vld_cnt + 1'b1;

                for (int i = 0; i < width; i ++)
                begin
                    queue.push_back (parallel_data[i]);
                end
            end

            if (serial_valid)
            begin
                out_vld_cnt <= out_vld_cnt + 1'b1;

                serial_data_expected = queue.pop_front ();

                if (serial_data !== serial_data_expected)
                begin
                    $display ("FAIL %s", `__FILE__);

                    $display ("++ TEST     => {%s, %s}",
                        `PB (serial_data), `PB (serial_data_expected));

                    $finish (1);
                end
            end
        end
    end

    //------------------------------------------------------------------------

    // Stimulus generation

    int current_inputs;
    logic               d_parallel_valid;
    logic [width - 1:0] d_parallel_data;

    initial
    begin
        `ifdef __ICARUS__
            // Uncomment the following line
            // to generate a VCD file and analyze it using GTKwave or Surfer

            $dumpvars;
        `endif

        parallel_valid <= 1'b0;
        parallel_data  <= 'x;

        d_parallel_data = '0;

        @ (negedge rst);

        while (current_inputs != n_inputs)
        begin
            if (current_inputs <= 10)
            begin
                d_parallel_valid = 1'b1;
                d_parallel_data  = { width { 1'b1 } } - d_parallel_data;
            end
            else
            begin
                d_parallel_valid = 1' ($urandom ());
                d_parallel_data  = width' ($urandom ());
            end

            current_inputs += 32' (d_parallel_valid);

            parallel_valid <= d_parallel_valid;
            parallel_data  <= d_parallel_valid ? d_parallel_data : 'x;

            @ (posedge clk);

            parallel_valid <= 1'b0;

            // repeat (width-1) @ (posedge clk);

            # 10

            while (busy === 1'b1)
            begin
                @ (posedge clk);
                # 10 ;
            end
        end

        // Stop driving and wait for output
        // We have to wait 2 cycles here: one to get an output from the module
        // and another one to wait for non-blocking assignment to out_vld_cnt
        parallel_valid <= '0;
        @(posedge clk);
        @(posedge clk);

        if (out_cnt_w' ( in_vld_cnt * width) !== out_vld_cnt) begin
            $display ("FAIL %s", `__FILE__);

            $display("++ TEST     => {%s != %s}", `PD(in_vld_cnt * width), `PD(out_vld_cnt));
            $display("++ EXPECTED => out_vld_cnt * width == in_vld_cnt");

            $finish (1);
        end

        $display ("PASS %s", `__FILE__);
        $finish;
    end

    //----------------------------------------------------------------------
    // Setting timeout against hangs

    initial
    begin
        repeat (100000) @ (posedge clk);
        $display ("FAIL %s: timeout reached!", `__FILE__);
        $finish;
    end

endmodule

02_sequential_basics/dump.vcd
$date
	Tue Mar 10 13:05:47 2026
$end
$version
	Icarus Verilog
$end
$timescale
	1s
$end
$scope module testbench $end
$var wire 1 ! serial_valid $end
$var wire 1 " serial_data $end
$var wire 1 # busy $end
$var parameter 32 $ in_cnt_w $end
$var parameter 32 % n_inputs $end
$var parameter 64 & n_outputs $end
$var parameter 32 ' out_cnt_w $end
$var parameter 32 ( width $end
$var reg 1 ) clk $end
$var reg 8 * d_parallel_data [7:0] $end
$var reg 1 + d_parallel_valid $end
$var reg 7 , in_vld_cnt [6:0] $end
$var reg 10 - out_vld_cnt [9:0] $end
$var reg 8 . parallel_data [7:0] $end
$var reg 1 / parallel_valid $end
$var reg 1 0 rst $end
$var reg 1 1 serial_data_expected $end
$var integer 32 2 current_inputs [31:0] $end
$var reg 1 3 was_reset $end
$scope module dut $end
$var wire 1 # busy $end
$var wire 1 ) clk $end
$var wire 8 4 parallel_data [7:0] $end
$var wire 1 / parallel_valid $end
$var wire 1 0 rst $end
$var wire 1 ! serial_valid $end
$var wire 1 " serial_data $end
$var parameter 32 5 width $end
$var reg 1 6 busy_reg $end
$var reg 3 7 cnt [2:0] $end
$var reg 8 8 data [7:0] $end
$upscope $end
$scope begin $ivl_for_loop0 $end
$var integer 32 9 i [31:0] $end
$upscope $end
$upscope $end
$enddefinitions $end
$comment Show the parameter values. $end
$dumpall
b1000 5
b1000 (
b1010 '
b1100100000 &
b1100100 %
b111 $
$end
#0
$dumpvars
b0 9
bx 8
bx 7
x6
bx 4
03
b0 2
x1
x0
0/
bx .
bx -
bx ,
x+
b0 *
0)
x#
x"
x!
$end
#500
1)
#1000
0)
#1500
0!
b0 7
0#
06
10
1)
#2000
0)
#2500
b0 -
b0 ,
13
1)
#3000
0)
#3500
1"
1!
b11111111 .
b11111111 4
1/
b1 2
b11111111 *
1+
00
1)
#4000
0)
#4500
1#
16
b1 7
b11111111 8
b1 -
b1 ,
0/
11
b1000 9
1)
#5000
0)
#5500
b10 7
b10 -
1)
#6000
0)
#6500
b11 7
b11 -
1)
#7000
0)
#7500
b100 7
b100 -
1)
#8000
0)
#8500
b101 7
b101 -
1)
#9000
0)
#9500
b110 7
b110 -
1)
#10000
0)
#10500
b111 7
b111 -
1)
#11000
0)
#11500
0!
0#
06
b1000 -
1)
#11510
0"
1!
b0 .
b0 4
1/
b10 2
b0 *
#12000
0)
#12500
1#
16
b1 7
b0 8
b1001 -
b10 ,
0/
01
b1000 9
1)
#13000
0)
#13500
b10 7
b1010 -
1)
#14000
0)
#14500
b11 7
b1011 -
1)
#15000
0)
#15500
b100 7
b1100 -
1)
#16000
0)
#16500
b101 7
b1101 -
1)
#17000
0)
#17500
b110 7
b1110 -
1)
#18000
0)
#18500
b111 7
b1111 -
1)
#19000
0)
#19500
0!
0#
06
b10000 -
1)
#19510
1"
1!
b11111111 .
b11111111 4
1/
b11 2
b11111111 *
#20000
0)
#20500
1#
16
b1 7
b11111111 8
b10001 -
b11 ,
0/
11
b1000 9
1)
#21000
0)
#21500
b10 7
b10010 -
1)
#22000
0)
#22500
b11 7
b10011 -
1)
#23000
0)
#23500
b100 7
b10100 -
1)
#24000
0)
#24500
b101 7
b10101 -
1)
#25000
0)
#25500
b110 7
b10110 -
1)
#26000
0)
#26500
b111 7
b10111 -
1)
#27000
0)
#27500
0!
0#
06
b11000 -
1)
#27510
0"
1!
b0 .
b0 4
1/
b100 2
b0 *
#28000
0)
#28500
1#
16
b1 7
b0 8
b11001 -
b100 ,
0/
01
b1000 9
1)
#29000
0)
#29500
b10 7
b11010 -
1)
#30000
0)
#30500
b11 7
b11011 -
1)
#31000
0)
#31500
b100 7
b11100 -
1)
#32000
0)
#32500
b101 7
b11101 -
1)
#33000
0)
#33500
b110 7
b11110 -
1)
#34000
0)
#34500
b111 7
b11111 -
1)
#35000
0)
#35500
0!
0#
06
b100000 -
1)
#35510
1"
1!
b11111111 .
b11111111 4
1/
b101 2
b11111111 *
#36000
0)
#36500
1#
16
b1 7
b11111111 8
b100001 -
b101 ,
0/
11
b1000 9
1)
#37000
0)
#37500
b10 7
b100010 -
1)
#38000
0)
#38500
b11 7
b100011 -
1)
#39000
0)
#39500
b100 7
b100100 -
1)
#40000
0)
#40500
b101 7
b100101 -
1)
#41000
0)
#41500
b110 7
b100110 -
1)
#42000
0)
#42500
b111 7
b100111 -
1)
#43000
0)
#43500
0!
0#
06
b101000 -
1)
#43510
0"
1!
b0 .
b0 4
1/
b110 2
b0 *
#44000
0)
#44500
1#
16
b1 7
b0 8
b101001 -
b110 ,
0/
01
b1000 9
1)
#45000
0)
#45500
b10 7
b101010 -
1)
#46000
0)
#46500
b11 7
b101011 -
1)
#47000
0)
#47500
b100 7
b101100 -
1)
#48000
0)
#48500
b101 7
b101101 -
1)
#49000
0)
#49500
b110 7
b101110 -
1)
#50000
0)
#50500
b111 7
b101111 -
1)
#51000
0)
#51500
0!
0#
06
b110000 -
1)
#51510
1"
1!
b11111111 .
b11111111 4
1/
b111 2
b11111111 *
#52000
0)
#52500
1#
16
b1 7
b11111111 8
b110001 -
b111 ,
0/
11
b1000 9
1)
#53000
0)
#53500
b10 7
b110010 -
1)
#54000
0)
#54500
b11 7
b110011 -
1)
#55000
0)
#55500
b100 7
b110100 -
1)
#56000
0)
#56500
b101 7
b110101 -
1)
#57000
0)
#57500
b110 7
b110110 -
1)
#58000
0)
#58500
b111 7
b110111 -
1)
#59000
0)
#59500
0!
0#
06
b111000 -
1)
#59510
0"
1!
b0 .
b0 4
1/
b1000 2
b0 *
#60000
0)
#60500
1#
16
b1 7
b0 8
b111001 -
b1000 ,
0/
01
b1000 9
1)
#61000
0)
#61500
b10 7
b111010 -
1)
#62000
0)
#62500
b11 7
b111011 -
1)
#63000
0)
#63500
b100 7
b111100 -
1)
#64000
0)
#64500
b101 7
b111101 -
1)
#65000
0)
#65500
b110 7
b111110 -
1)
#66000
0)
#66500
b111 7
b111111 -
1)
#67000
0)
#67500
0!
0#
06
b1000000 -
1)
#67510
1"
1!
b11111111 .
b11111111 4
1/
b1001 2
b11111111 *
#68000
0)
#68500
1#
16
b1 7
b11111111 8
b1000001 -
b1001 ,
0/
11
b1000 9
1)
#69000
0)
#69500
b10 7
b1000010 -
1)
#70000
0)
#70500
b11 7
b1000011 -
1)
#71000
0)
#71500
b100 7
b1000100 -
1)
#72000
0)
#72500
b101 7
b1000101 -
1)
#73000
0)
#73500
b110 7
b1000110 -
1)
#74000
0)
#74500
b111 7
b1000111 -
1)
#75000
0)
#75500
0!
0#
06
b1001000 -
1)
#75510
0"
1!
b0 .
b0 4
1/
b1010 2
b0 *
#76000
0)
#76500
1#
16
b1 7
b0 8
b1001001 -
b1010 ,
0/
01
b1000 9
1)
#77000
0)
#77500
b10 7
b1001010 -
1)
#78000
0)
#78500
b11 7
b1001011 -
1)
#79000
0)
#79500
b100 7
b1001100 -
1)
#80000
0)
#80500
b101 7
b1001101 -
1)
#81000
0)
#81500
b110 7
b1001110 -
1)
#82000
0)
#82500
b111 7
b1001111 -
1)
#83000
0)
#83500
0!
0#
06
b1010000 -
1)
#83510
1"
1!
b11111111 .
b11111111 4
1/
b1011 2
b11111111 *
#84000
0)
#84500
1#
16
b1 7
b11111111 8
b1010001 -
b1011 ,
0/
11
b1000 9
1)
#85000
0)
#85500
b10 7
b1010010 -
1)
#86000
0)
#86500
b11 7
b1010011 -
1)
#87000
0)
#87500
b100 7
b1010100 -
1)
#88000
0)
#88500
b101 7
b1010101 -
1)
#89000
0)
#89500
b110 7
b1010110 -
1)
#90000
0)
#90500
b111 7
b1010111 -
1)
#91000
0)
#91500
0!
0#
06
b1011000 -
1)
#91510
bx .
bx 4
b10000001 *
0+
#92000
0)
#92500
1)
#92510
1!
b1100011 .
b1100011 4
1/
b1100 2
b1100011 *
1+
#93000
0)
#93500
1#
16
b1 7
b1100011 8
b1011001 -
b1100 ,
0/
b1000 9
1)
#94000
0)
#94500
0"
b10 7
b1011010 -
1)
#95000
0)
#95500
b11 7
b1011011 -
01
1)
#96000
0)
#96500
b100 7
b1011100 -
1)
#97000
0)
#97500
1"
b101 7
b1011101 -
1)
#98000
0)
#98500
b110 7
b1011110 -
11
1)
#99000
0)
#99500
0"
b111 7
b1011111 -
1)
#100000
0)
#100500
0!
0#
06
b1100000 -
01
1)
#100510
1"
1!
b10001101 .
b10001101 4
1/
b1101 2
b10001101 *
#101000
0)
#101500
0"
1#
16
b1 7
b10001101 8
b1100001 -
b1101 ,
0/
11
b1000 9
1)
#102000
0)
#102500
1"
b10 7
b1100010 -
01
1)
#103000
0)
#103500
b11 7
b1100011 -
11
1)
#104000
0)
#104500
0"
b100 7
b1100100 -
1)
#105000
0)
#105500
b101 7
b1100101 -
01
1)
#106000
0)
#106500
b110 7
b1100110 -
1)
#107000
0)
#107500
1"
b111 7
b1100111 -
1)
#108000
0)
#108500
0!
0#
06
b1101000 -
11
1)
#108510
0"
1!
b10010 .
b10010 4
1/
b1110 2
b10010 *
#109000
0)
#109500
1"
1#
16
b1 7
b10010 8
b1101001 -
b1110 ,
0/
01
b1000 9
1)
#110000
0)
#110500
0"
b10 7
b1101010 -
11
1)
#111000
0)
#111500
b11 7
b1101011 -
01
1)
#112000
0)
#112500
1"
b100 7
b1101100 -
1)
#113000
0)
#113500
0"
b101 7
b1101101 -
11
1)
#114000
0)
#114500
b110 7
b1101110 -
01
1)
#115000
0)
#115500
b111 7
b1101111 -
1)
#116000
0)
#116500
0!
0#
06
b1110000 -
1)
#116510
1"
1!
b1101 .
b1101 4
1/
b1111 2
b1101 *
#117000
0)
#117500
0"
1#
16
b1 7
b1101 8
b1110001 -
b1111 ,
0/
11
b1000 9
1)
#118000
0)
#118500
1"
b10 7
b1110010 -
01
1)
#119000
0)
#119500
b11 7
b1110011 -
11
1)
#120000
0)
#120500
0"
b100 7
b1110100 -
1)
#121000
0)
#121500
b101 7
b1110101 -
01
1)
#122000
0)
#122500
b110 7
b1110110 -
1)
#123000
0)
#123500
b111 7
b1110111 -
1)
#124000
0)
#124500
0!
0#
06
b1111000 -
1)
#124510
bx .
bx 4
b111101 *
0+
#125000
0)
#125500
1)
#125510
1!
b10001100 .
b10001100 4
1/
b10000 2
b10001100 *
1+
#126000
0)
#126500
1#
16
b1 7
b10001100 8
b1111001 -
b10000 ,
0/
b1000 9
1)
#127000
0)
#127500
1"
b10 7
b1111010 -
1)
#128000
0)
#128500
b11 7
b1111011 -
11
1)
#129000
0)
#129500
0"
b100 7
b1111100 -
1)
#130000
0)
#130500
b101 7
b1111101 -
01
1)
#131000
0)
#131500
b110 7
b1111110 -
1)
#132000
0)
#132500
1"
b111 7
b1111111 -
1)
#133000
0)
#133500
0!
0#
06
b10000000 -
11
1)
#133510
0"
1!
b11000110 .
b11000110 4
1/
b10001 2
b11000110 *
#134000
0)
#134500
1"
1#
16
b1 7
b11000110 8
b10000001 -
b10001 ,
0/
01
b1000 9
1)
#135000
0)
#135500
b10 7
b10000010 -
11
1)
#136000
0)
#136500
0"
b11 7
b10000011 -
1)
#137000
0)
#137500
b100 7
b10000100 -
01
1)
#138000
0)
#138500
b101 7
b10000101 -
1)
#139000
0)
#139500
1"
b110 7
b10000110 -
1)
#140000
0)
#140500
b111 7
b10000111 -
11
1)
#141000
0)
#141500
0!
0#
06
b10001000 -
1)
#141510
0"
1!
b10101010 .
b10101010 4
1/
b10010 2
b10101010 *
#142000
0)
#142500
1"
1#
16
b1 7
b10101010 8
b10001001 -
b10010 ,
0/
01
b1000 9
1)
#143000
0)
#143500
0"
b10 7
b10001010 -
11
1)
#144000
0)
#144500
1"
b11 7
b10001011 -
01
1)
#145000
0)
#145500
0"
b100 7
b10001100 -
11
1)
#146000
0)
#146500
1"
b101 7
b10001101 -
01
1)
#147000
0)
#147500
0"
b110 7
b10001110 -
11
1)
#148000
0)
#148500
1"
b111 7
b10001111 -
01
1)
#149000
0)
#149500
0!
0#
06
b10010000 -
11
1)
#149510
1!
b1110111 .
b1110111 4
1/
b10011 2
b1110111 *
#150000
0)
#150500
1#
16
b1 7
b1110111 8
b10010001 -
b10011 ,
0/
b1000 9
1)
#151000
0)
#151500
b10 7
b10010010 -
1)
#152000
0)
#152500
0"
b11 7
b10010011 -
1)
#153000
0)
#153500
1"
b100 7
b10010100 -
01
1)
#154000
0)
#154500
b101 7
b10010101 -
11
1)
#155000
0)
#155500
b110 7
b10010110 -
1)
#156000
0)
#156500
0"
b111 7
b10010111 -
1)
#157000
0)
#157500
0!
0#
06
b10011000 -
01
1)
#157510
bx .
bx 4
b10001111 *
0+
#158000
0)
#158500
1)
#158510
b11001110 *
#159000
0)
#159500
1)
#159510
b11000101 *
#160000
0)
#160500
1)
#160510
b10111101 *
#161000
0)
#161500
1)
#161510
1"
1!
b1100101 .
b1100101 4
1/
b10100 2
b1100101 *
1+
#162000
0)
#162500
0"
1#
16
b1 7
b1100101 8
b10011001 -
b10100 ,
0/
11
b1000 9
1)
#163000
0)
#163500
1"
b10 7
b10011010 -
01
1)
#164000
0)
#164500
0"
b11 7
b10011011 -
11
1)
#165000
0)
#165500
b100 7
b10011100 -
01
1)
#166000
0)
#166500
1"
b101 7
b10011101 -
1)
#167000
0)
#167500
b110 7
b10011110 -
11
1)
#168000
0)
#168500
0"
b111 7
b10011111 -
1)
#169000
0)
#169500
0!
0#
06
b10100000 -
01
1)
#169510
1!
b1010 .
b1010 4
1/
b10101 2
b1010 *
#170000
0)
#170500
1"
1#
16
b1 7
b1010 8
b10100001 -
b10101 ,
0/
b1000 9
1)
#171000
0)
#171500
0"
b10 7
b10100010 -
11
1)
#172000
0)
#172500
1"
b11 7
b10100011 -
01
1)
#173000
0)
#173500
0"
b100 7
b10100100 -
11
1)
#174000
0)
#174500
b101 7
b10100101 -
01
1)
#175000
0)
#175500
b110 7
b10100110 -
1)
#176000
0)
#176500
b111 7
b10100111 -
1)
#177000
0)
#177500
0!
0#
06
b10101000 -
1)
#177510
bx .
bx 4
b100000 *
0+
#178000
0)
#178500
1)
#178510
b10011101 *
#179000
0)
#179500
1)
#179510
b10011 *
#180000
0)
#180500
1)
#180510
1"
1!
b1010011 .
b1010011 4
1/
b10110 2
b1010011 *
1+
#181000
0)
#181500
1#
16
b1 7
b1010011 8
b10101001 -
b10110 ,
0/
11
b1000 9
1)
#182000
0)
#182500
0"
b10 7
b10101010 -
1)
#183000
0)
#183500
b11 7
b10101011 -
01
1)
#184000
0)
#184500
1"
b100 7
b10101100 -
1)
#185000
0)
#185500
0"
b101 7
b10101101 -
11
1)
#186000
0)
#186500
1"
b110 7
b10101110 -
01
1)
#187000
0)
#187500
0"
b111 7
b10101111 -
11
1)
#188000
0)
#188500
0!
0#
06
b10110000 -
01
1)
#188510
1"
1!
b11010101 .
b11010101 4
1/
b10111 2
b11010101 *
#189000
0)
#189500
0"
1#
16
b1 7
b11010101 8
b10110001 -
b10111 ,
0/
11
b1000 9
1)
#190000
0)
#190500
1"
b10 7
b10110010 -
01
1)
#191000
0)
#191500
0"
b11 7
b10110011 -
11
1)
#192000
0)
#192500
1"
b100 7
b10110100 -
01
1)
#193000
0)
#193500
0"
b101 7
b10110101 -
11
1)
#194000
0)
#194500
1"
b110 7
b10110110 -
01
1)
#195000
0)
#195500
b111 7
b10110111 -
11
1)
#196000
0)
#196500
0!
0#
06
b10111000 -
1)
#196510
bx .
bx 4
b10101110 *
0+
#197000
0)
#197500
1)
#197510
1!
b11001111 .
b11001111 4
1/
b11000 2
b11001111 *
1+
#198000
0)
#198500
1#
16
b1 7
b11001111 8
b10111001 -
b11000 ,
0/
b1000 9
1)
#199000
0)
#199500
b10 7
b10111010 -
1)
#200000
0)
#200500
b11 7
b10111011 -
1)
#201000
0)
#201500
0"
b100 7
b10111100 -
1)
#202000
0)
#202500
b101 7
b10111101 -
01
1)
#203000
0)
#203500
1"
b110 7
b10111110 -
1)
#204000
0)
#204500
b111 7
b10111111 -
11
1)
#205000
0)
#205500
0!
0#
06
b11000000 -
1)
#205510
0"
1!
b1010 .
b1010 4
1/
b11001 2
b1010 *
#206000
0)
#206500
1"
1#
16
b1 7
b1010 8
b11000001 -
b11001 ,
0/
01
b1000 9
1)
#207000
0)
#207500
0"
b10 7
b11000010 -
11
1)
#208000
0)
#208500
1"
b11 7
b11000011 -
01
1)
#209000
0)
#209500
0"
b100 7
b11000100 -
11
1)
#210000
0)
#210500
b101 7
b11000101 -
01
1)
#211000
0)
#211500
b110 7
b11000110 -
1)
#212000
0)
#212500
b111 7
b11000111 -
1)
#213000
0)
#213500
0!
0#
06
b11001000 -
1)
#213510
bx .
bx 4
b111100 *
0+
#214000
0)
#214500
1)
#214510
b10001010 *
#215000
0)
#215500
1)
#215510
1!
b11011000 .
b11011000 4
1/
b11010 2
b11011000 *
1+
#216000
0)
#216500
1#
16
b1 7
b11011000 8
b11001001 -
b11010 ,
0/
b1000 9
1)
#217000
0)
#217500
b10 7
b11001010 -
1)
#218000
0)
#218500
1"
b11 7
b11001011 -
1)
#219000
0)
#219500
b100 7
b11001100 -
11
1)
#220000
0)
#220500
0"
b101 7
b11001101 -
1)
#221000
0)
#221500
1"
b110 7
b11001110 -
01
1)
#222000
0)
#222500
b111 7
b11001111 -
11
1)
#223000
0)
#223500
0!
0#
06
b11010000 -
1)
#223510
bx .
bx 4
b10001001 *
0+
#224000
0)
#224500
1)
#224510
0"
1!
b10110110 .
b10110110 4
1/
b11011 2
b10110110 *
1+
#225000
0)
#225500
1"
1#
16
b1 7
b10110110 8
b11010001 -
b11011 ,
0/
01
b1000 9
1)
#226000
0)
#226500
b10 7
b11010010 -
11
1)
#227000
0)
#227500
0"
b11 7
b11010011 -
1)
#228000
0)
#228500
1"
b100 7
b11010100 -
01
1)
#229000
0)
#229500
b101 7
b11010101 -
11
1)
#230000
0)
#230500
0"
b110 7
b11010110 -
1)
#231000
0)
#231500
1"
b111 7
b11010111 -
01
1)
#232000
0)
#232500
0!
0#
06
b11011000 -
11
1)
#232510
bx .
bx 4
b10101110 *
0+
#233000
0)
#233500
1)
#233510
b101010 *
#234000
0)
#234500
1)
#234510
1!
b1110001 .
b1110001 4
1/
b11100 2
b1110001 *
1+
#235000
0)
#235500
0"
1#
16
b1 7
b1110001 8
b11011001 -
b11100 ,
0/
b1000 9
1)
#236000
0)
#236500
b10 7
b11011010 -
01
1)
#237000
0)
#237500
b11 7
b11011011 -
1)
#238000
0)
#238500
1"
b100 7
b11011100 -
1)
#239000
0)
#239500
b101 7
b11011101 -
11
1)
#240000
0)
#240500
b110 7
b11011110 -
1)
#241000
0)
#241500
0"
b111 7
b11011111 -
1)
#242000
0)
#242500
0!
0#
06
b11100000 -
01
1)
#242510
1"
1!
b1001111 .
b1001111 4
1/
b11101 2
b1001111 *
#243000
0)
#243500
1#
16
b1 7
b1001111 8
b11100001 -
b11101 ,
0/
11
b1000 9
1)
#244000
0)
#244500
b10 7
b11100010 -
1)
#245000
0)
#245500
b11 7
b11100011 -
1)
#246000
0)
#246500
0"
b100 7
b11100100 -
1)
#247000
0)
#247500
b101 7
b11100101 -
01
1)
#248000
0)
#248500
1"
b110 7
b11100110 -
1)
#249000
0)
#249500
0"
b111 7
b11100111 -
11
1)
#250000
0)
#250500
0!
0#
06
b11101000 -
01
1)
#250510
1!
b111010 .
b111010 4
1/
b11110 2
b111010 *
#251000
0)
#251500
1"
1#
16
b1 7
b111010 8
b11101001 -
b11110 ,
0/
b1000 9
1)
#252000
0)
#252500
0"
b10 7
b11101010 -
11
1)
#253000
0)
#253500
1"
b11 7
b11101011 -
01
1)
#254000
0)
#254500
b100 7
b11101100 -
11
1)
#255000
0)
#255500
b101 7
b11101101 -
1)
#256000
0)
#256500
0"
b110 7
b11101110 -
1)
#257000
0)
#257500
b111 7
b11101111 -
01
1)
#258000
0)
#258500
0!
0#
06
b11110000 -
1)
#258510
bx .
bx 4
b10101 *
0+
#259000
0)
#259500
1)
#259510
1"
1!
b11011001 .
b11011001 4
1/
b11111 2
b11011001 *
1+
#260000
0)
#260500
0"
1#
16
b1 7
b11011001 8
b11110001 -
b11111 ,
0/
11
b1000 9
1)
#261000
0)
#261500
b10 7
b11110010 -
01
1)
#262000
0)
#262500
1"
b11 7
b11110011 -
1)
#263000
0)
#263500
b100 7
b11110100 -
11
1)
#264000
0)
#264500
0"
b101 7
b11110101 -
1)
#265000
0)
#265500
1"
b110 7
b11110110 -
01
1)
#266000
0)
#266500
b111 7
b11110111 -
11
1)
#267000
0)
#267500
0!
0#
06
b11111000 -
1)
#267510
bx .
bx 4
b1001100 *
0+
#268000
0)
#268500
1)
#268510
1!
b10001111 .
b10001111 4
1/
b100000 2
b10001111 *
1+
#269000
0)
#269500
1#
16
b1 7
b10001111 8
b11111001 -
b100000 ,
0/
b1000 9
1)
#270000
0)
#270500
b10 7
b11111010 -
1)
#271000
0)
#271500
b11 7
b11111011 -
1)
#272000
0)
#272500
0"
b100 7
b11111100 -
1)
#273000
0)
#273500
b101 7
b11111101 -
01
1)
#274000
0)
#274500
b110 7
b11111110 -
1)
#275000
0)
#275500
1"
b111 7
b11111111 -
1)
#276000
0)
#276500
0!
0#
06
b100000000 -
11
1)
#276510
bx .
bx 4
b10110111 *
0+
#277000
0)
#277500
1)
#277510
0"
1!
b1011100 .
b1011100 4
1/
b100001 2
b1011100 *
1+
#278000
0)
#278500
1#
16
b1 7
b1011100 8
b100000001 -
b100001 ,
0/
01
b1000 9
1)
#279000
0)
#279500
1"
b10 7
b100000010 -
1)
#280000
0)
#280500
b11 7
b100000011 -
11
1)
#281000
0)
#281500
b100 7
b100000100 -
1)
#282000
0)
#282500
0"
b101 7
b100000101 -
1)
#283000
0)
#283500
1"
b110 7
b100000110 -
01
1)
#284000
0)
#284500
0"
b111 7
b100000111 -
11
1)
#285000
0)
#285500
0!
0#
06
b100001000 -
01
1)
#285510
1"
1!
b10001001 .
b10001001 4
1/
b100010 2
b10001001 *
#286000
0)
#286500
0"
1#
16
b1 7
b10001001 8
b100001001 -
b100010 ,
0/
11
b1000 9
1)
#287000
0)
#287500
b10 7
b100001010 -
01
1)
#288000
0)
#288500
1"
b11 7
b100001011 -
1)
#289000
0)
#289500
0"
b100 7
b100001100 -
11
1)
#290000
0)
#290500
b101 7
b100001101 -
01
1)
#291000
0)
#291500
b110 7
b100001110 -
1)
#292000
0)
#292500
1"
b111 7
b100001111 -
1)
#293000
0)
#293500
0!
0#
06
b100010000 -
11
1)
#293510
0"
1!
b11010000 .
b11010000 4
1/
b100011 2
b11010000 *
#294000
0)
#294500
1#
16
b1 7
b11010000 8
b100010001 -
b100011 ,
0/
01
b1000 9
1)
#295000
0)
#295500
b10 7
b100010010 -
1)
#296000
0)
#296500
b11 7
b100010011 -
1)
#297000
0)
#297500
1"
b100 7
b100010100 -
1)
#298000
0)
#298500
0"
b101 7
b100010101 -
11
1)
#299000
0)
#299500
1"
b110 7
b100010110 -
01
1)
#300000
0)
#300500
b111 7
b100010111 -
11
1)
#301000
0)
#301500
0!
0#
06
b100011000 -
1)
#301510
1!
b1010001 .
b1010001 4
1/
b100100 2
b1010001 *
#302000
0)
#302500
0"
1#
16
b1 7
b1010001 8
b100011001 -
b100100 ,
0/
b1000 9
1)
#303000
0)
#303500
b10 7
b100011010 -
01
1)
#304000
0)
#304500
b11 7
b100011011 -
1)
#305000
0)
#305500
1"
b100 7
b100011100 -
1)
#306000
0)
#306500
0"
b101 7
b100011101 -
11
1)
#307000
0)
#307500
1"
b110 7
b100011110 -
01
1)
#308000
0)
#308500
0"
b111 7
b100011111 -
11
1)
#309000
0)
#309500
0!
0#
06
b100100000 -
01
1)
#309510
bx .
bx 4
b1100 *
0+
#310000
0)
#310500
1)
#310510
b11001000 *
#311000
0)
#311500
1)
#311510
1"
1!
b111101 .
b111101 4
1/
b100101 2
b111101 *
1+
#312000
0)
#312500
0"
1#
16
b1 7
b111101 8
b100100001 -
b100101 ,
0/
11
b1000 9
1)
#313000
0)
#313500
1"
b10 7
b100100010 -
01
1)
#314000
0)
#314500
b11 7
b100100011 -
11
1)
#315000
0)
#315500
b100 7
b100100100 -
1)
#316000
0)
#316500
b101 7
b100100101 -
1)
#317000
0)
#317500
0"
b110 7
b100100110 -
1)
#318000
0)
#318500
b111 7
b100100111 -
01
1)
#319000
0)
#319500
0!
0#
06
b100101000 -
1)
#319510
bx .
bx 4
b1111110 *
0+
#320000
0)
#320500
1)
#320510
1"
1!
b111001 .
b111001 4
1/
b100110 2
b111001 *
1+
#321000
0)
#321500
0"
1#
16
b1 7
b111001 8
b100101001 -
b100110 ,
0/
11
b1000 9
1)
#322000
0)
#322500
b10 7
b100101010 -
01
1)
#323000
0)
#323500
1"
b11 7
b100101011 -
1)
#324000
0)
#324500
b100 7
b100101100 -
11
1)
#325000
0)
#325500
b101 7
b100101101 -
1)
#326000
0)
